immichpy/.openapi-generator/FILES
immichpy/.openapi-generator/VERSION
immichpy/__init__.py
immichpy/cli/__main__.py
immichpy/cli/commands/activities.py
immichpy/cli/commands/albums.py
immichpy/cli/commands/api_keys.py
immichpy/cli/commands/assets.py
immichpy/cli/commands/authentication.py
immichpy/cli/commands/authentication_admin.py
immichpy/cli/commands/database_backups_admin.py
immichpy/cli/commands/download.py
immichpy/cli/commands/duplicates.py
immichpy/cli/commands/faces.py
immichpy/cli/commands/jobs.py
immichpy/cli/commands/libraries.py
immichpy/cli/commands/maintenance_admin.py
immichpy/cli/commands/map.py
immichpy/cli/commands/memories.py
immichpy/cli/commands/notifications.py
immichpy/cli/commands/notifications_admin.py
immichpy/cli/commands/partners.py
immichpy/cli/commands/people.py
immichpy/cli/commands/plugins.py
immichpy/cli/commands/queues.py
immichpy/cli/commands/search.py
immichpy/cli/commands/server.py
immichpy/cli/commands/sessions.py
immichpy/cli/commands/shared_links.py
immichpy/cli/commands/stacks.py
immichpy/cli/commands/sync.py
immichpy/cli/commands/system_config.py
immichpy/cli/commands/system_metadata.py
immichpy/cli/commands/tags.py
immichpy/cli/commands/timeline.py
immichpy/cli/commands/trash.py
immichpy/cli/commands/users.py
immichpy/cli/commands/users_admin.py
immichpy/cli/commands/views.py
immichpy/cli/commands/workflows.py
immichpy/cli/consts.py
immichpy/cli/main.py
immichpy/cli/runtime.py
immichpy/cli/types.py
immichpy/cli/utils.py
immichpy/cli/wrapper/assets.py
immichpy/cli/wrapper/config.py
immichpy/cli/wrapper/download.py
immichpy/cli/wrapper/setup.py
immichpy/cli/wrapper/users.py
immichpy/client/.openapi-generator/FILES
immichpy/client/.openapi-generator/VERSION
immichpy/client/.openapi-generator-ignore
immichpy/client/__init__.py
immichpy/client/consts.py
immichpy/client/generated/__init__.py
immichpy/client/generated/api/__init__.py
immichpy/client/generated/api/activities_api.py
immichpy/client/generated/api/albums_api.py
immichpy-2.0.0.dist-info/licenses/LICENSE
immichpy-2.0.0.dist-info/WHEEL
immichpy-2.0.0.dist-info/entry_points.txt
immichpy-2.0.0.dist-info/METADATA
immichpy-2.0.0.dist-info/RECORD
