Metadata-Version: 2.4
Name: immichpy
Version: 2.0.0
Summary: The stable, typed Python API layer for Immich automation and integrations.
Keywords: immich,photos,backup,client,api,cli,automation,integrations
Author: Timon Rieger
Author-email: Timon Rieger <contact@timonrieger.de>
License-Expression: MIT
License-File: LICENSE
Classifier: Topic :: Multimedia
Classifier: Topic :: Software Development :: Libraries
Classifier: Development Status :: 4 - Beta
Classifier: Intended Audience :: Developers
Classifier: Operating System :: OS Independent
Classifier: Programming Language :: Python :: 3.10
Classifier: Programming Language :: Python :: 3.11
Classifier: Programming Language :: Python :: 3.12
Classifier: Programming Language :: Python :: 3.13
Classifier: Programming Language :: Python :: 3.14
Classifier: Typing :: Typed
Requires-Dist: aiohttp>=3.8.4,<4.0.0
Requires-Dist: aiohttp-retry>=2.8.3,<3.0.0
Requires-Dist: pydantic>=2.0.0,<3.0.0
Requires-Dist: pystatx>=0.1,<0.2
Requires-Dist: python-dateutil>=2.8.2,<3.0.0
Requires-Dist: rich>=14.2.0,<15.0.0
Requires-Dist: typing-extensions>=4.7.1,<5.0.0
Requires-Dist: uv==0.9.28 ; extra == 'build'
Requires-Dist: rtoml>=0.13.0,<0.14.0 ; extra == 'cli'
Requires-Dist: typer>=0.21.1,<0.22.0 ; extra == 'cli'
Requires-Python: >=3.10
Project-URL: Repository, https://github.com/timonrieger/immichpy
Project-URL: Changelog, https://github.com/timonrieger/immichpy/releases
Provides-Extra: build
Provides-Extra: cli
